{
  "density_gap": 10,
  "density_name": "sparse_gap10",
  "generated_h5ad": "generated.h5ad",
  "label_support_labels": [
    "15 HY Gnrh1 Glut"
  ],
  "lower_ref_slice": 31,
  "mean_corr": 0.9794911730182931,
  "median_gene_pearson": 0.12923882733888498,
  "median_gene_spearman": 0.12157876355276825,
  "moran_corr": 0.7559168719544929,
  "n_genes": 1122,
  "n_label_support_records": 1,
  "n_spots": 9533,
  "per_class_metrics_csv": "per_class_metrics.csv",
  "per_gene_metrics_csv": "per_gene_metrics.csv",
  "random_seed": 102029,
  "ref_z_gap": 1.0247416036921946,
  "target_slice": 36,
  "target_z": 2.760884455979676,
  "tau": 0.47896993865873555,
  "upper_ref_slice": 41,
  "var_corr": 0.9055058860478332,
  "z0": 2.2700640329181714,
  "z1": 3.294805636610366,
  "zero_ks": 0.11764705882352941
}
